{
  "variants": {
    "facing=up,rotation=0,has_filter=false":    { "model": "create_fanta:block/without_filter_block" },
    "facing=up,rotation=0,has_filter=true":     { "model": "create_fanta:block/filter_block" },
    "facing=up,rotation=1,has_filter=false":    { "model": "create_fanta:block/without_filter_block", "y": 90 },
    "facing=up,rotation=1,has_filter=true":     { "model": "create_fanta:block/filter_block", "y": 90 },
    "facing=up,rotation=2,has_filter=false":    { "model": "create_fanta:block/without_filter_block", "y": 180 },
    "facing=up,rotation=2,has_filter=true":     { "model": "create_fanta:block/filter_block", "y": 180 },
    "facing=up,rotation=3,has_filter=false":    { "model": "create_fanta:block/without_filter_block", "y": 270 },
    "facing=up,rotation=3,has_filter=true":     { "model": "create_fanta:block/filter_block", "y": 270 },

    "facing=down,rotation=0,has_filter=false":  { "model": "create_fanta:block/without_filter_block", "x": 180 },
    "facing=down,rotation=0,has_filter=true":   { "model": "create_fanta:block/filter_block", "x": 180 },
    "facing=down,rotation=1,has_filter=false":  { "model": "create_fanta:block/without_filter_block", "x": 180, "y": 90 },
    "facing=down,rotation=1,has_filter=true":   { "model": "create_fanta:block/filter_block", "x": 180, "y": 90 },
    "facing=down,rotation=2,has_filter=false":  { "model": "create_fanta:block/without_filter_block", "x": 180, "y": 180 },
    "facing=down,rotation=2,has_filter=true":   { "model": "create_fanta:block/filter_block", "x": 180, "y": 180 },
    "facing=down,rotation=3,has_filter=false":  { "model": "create_fanta:block/without_filter_block", "x": 180, "y": 270 },
    "facing=down,rotation=3,has_filter=true":   { "model": "create_fanta:block/filter_block", "x": 180, "y": 270 },

    "facing=north,rotation=0,has_filter=false": { "model": "create_fanta:block/without_filter_block", "x": 90, "y": 180 },
    "facing=north,rotation=0,has_filter=true":  { "model": "create_fanta:block/filter_block", "x": 90, "y": 180 },
    "facing=north,rotation=1,has_filter=false": { "model": "create_fanta:block/without_filter_block", "x": 90, "y": 180 },
    "facing=north,rotation=1,has_filter=true":  { "model": "create_fanta:block/filter_block", "x": 90, "y": 180 },
    "facing=north,rotation=2,has_filter=false": { "model": "create_fanta:block/without_filter_block", "x": 90, "y": 180 },
    "facing=north,rotation=2,has_filter=true":  { "model": "create_fanta:block/filter_block", "x": 90, "y": 180 },
    "facing=north,rotation=3,has_filter=false": { "model": "create_fanta:block/without_filter_block", "x": 90, "y": 180 },
    "facing=north,rotation=3,has_filter=true":  { "model": "create_fanta:block/filter_block", "x": 90, "y": 180 },

    "facing=south,rotation=0,has_filter=false": { "model": "create_fanta:block/without_filter_block", "x": 90 },
    "facing=south,rotation=0,has_filter=true":  { "model": "create_fanta:block/filter_block", "x": 90 },
    "facing=south,rotation=1,has_filter=false": { "model": "create_fanta:block/without_filter_block", "x": 90 },
    "facing=south,rotation=1,has_filter=true":  { "model": "create_fanta:block/filter_block", "x": 90 },
    "facing=south,rotation=2,has_filter=false": { "model": "create_fanta:block/without_filter_block", "x": 90 },
    "facing=south,rotation=2,has_filter=true":  { "model": "create_fanta:block/filter_block", "x": 90 },
    "facing=south,rotation=3,has_filter=false": { "model": "create_fanta:block/without_filter_block", "x": 90 },
    "facing=south,rotation=3,has_filter=true":  { "model": "create_fanta:block/filter_block", "x": 90 },

    "facing=east,rotation=0,has_filter=false":  { "model": "create_fanta:block/without_filter_block", "x": 90, "y": 90 },
    "facing=east,rotation=0,has_filter=true":   { "model": "create_fanta:block/filter_block", "x": 90, "y": 90 },
    "facing=east,rotation=1,has_filter=false":  { "model": "create_fanta:block/without_filter_block", "x": 90, "y": 90 },
    "facing=east,rotation=1,has_filter=true":   { "model": "create_fanta:block/filter_block", "x": 90, "y": 90 },
    "facing=east,rotation=2,has_filter=false":  { "model": "create_fanta:block/without_filter_block", "x": 90, "y": 90 },
    "facing=east,rotation=2,has_filter=true":   { "model": "create_fanta:block/filter_block", "x": 90, "y": 90 },
    "facing=east,rotation=3,has_filter=false":  { "model": "create_fanta:block/without_filter_block", "x": 90, "y": 90 },
    "facing=east,rotation=3,has_filter=true":   { "model": "create_fanta:block/filter_block", "x": 90, "y": 90 },

    "facing=west,rotation=0,has_filter=false":  { "model": "create_fanta:block/without_filter_block", "x": 90, "y": 270 },
    "facing=west,rotation=0,has_filter=true":   { "model": "create_fanta:block/filter_block", "x": 90, "y": 270 },
    "facing=west,rotation=1,has_filter=false":  { "model": "create_fanta:block/without_filter_block", "x": 90, "y": 270 },
    "facing=west,rotation=1,has_filter=true":   { "model": "create_fanta:block/filter_block", "x": 90, "y": 270 },
    "facing=west,rotation=2,has_filter=false":  { "model": "create_fanta:block/without_filter_block", "x": 90, "y": 270 },
    "facing=west,rotation=2,has_filter=true":   { "model": "create_fanta:block/filter_block", "x": 90, "y": 270 },
    "facing=west,rotation=3,has_filter=false":  { "model": "create_fanta:block/without_filter_block", "x": 90, "y": 270 },
    "facing=west,rotation=3,has_filter=true":   { "model": "create_fanta:block/filter_block", "x": 90, "y": 270 }
  }
}